costack_sdk/__init__.py
costack_sdk/costack_lambda/__init__.py
costack_sdk/costack_lambda/context.py
costack_sdk/costack_lambda/function.py
costack_sdk/costack_lambda/main.py
costack_sdk/costack_workflow/__init__.py
costack_sdk/costack_workflow/constants.py
costack_sdk/costack_workflow/context/__init__.py
costack_sdk/costack_workflow/context/function_context.py
costack_sdk/costack_workflow/context/runtime_context.py
costack_sdk/costack_workflow/lambda_runtime.py
costack_sdk/costack_workflow/step.py
costack_sdk/integrations/DynamoDB.py
costack_sdk/integrations/SMTP.py
costack_sdk/integrations/main.py
costack_sdk/integrations/slack.py
costack_sdk-0.2.0.dist-info/WHEEL
costack_sdk-0.2.0.dist-info/METADATA
costack_sdk-0.2.0.dist-info/RECORD
